pyndler/__init__.py
pyndler/builder.py
pyndler/cli.py
pyndler/rcedit/__init__.py
pyndler/rcedit/rcedit-x32.exe
pyndler/rcedit/rcedit-x64.exe
pyndler-0.1.0.dist-info/LICENSE
pyndler-0.1.0.dist-info/METADATA
pyndler-0.1.0.dist-info/WHEEL
pyndler-0.1.0.dist-info/entry_points.txt
pyndler-0.1.0.dist-info/top_level.txt
pyndler-0.1.0.dist-info/RECORD
