Metadata-Version: 2.1
Name: pyndler
Version: 0.1.0
Summary: Executable bundler for Windows
Home-page: https://github.com/codetent/pyndler
Author: codetent
License: MIT
Platform: Windows
Classifier: Development Status :: 4 - Beta
Classifier: Intended Audience :: Developers
Classifier: License :: OSI Approved :: MIT License
Classifier: Operating System :: Microsoft :: Windows
Classifier: Programming Language :: Python :: 3
Classifier: Topic :: Software Development :: Build Tools
Requires-Python: >=3.7
Requires-Dist: plumbum
Provides-Extra: test
Requires-Dist: pytest ; extra == 'test'
Requires-Dist: pytest-cov ; extra == 'test'
Requires-Dist: flake8 ; extra == 'test'
Requires-Dist: flake8-annotations ; extra == 'test'
Requires-Dist: flake8-comprehensions ; extra == 'test'
Requires-Dist: flake8-docstrings ; extra == 'test'
Requires-Dist: flake8-raise ; extra == 'test'
Requires-Dist: flake8-typing-imports ; extra == 'test'
